tic_toc/Timer.py
tic_toc/__init__.py
tic_toc-0.1.2.data/data/license.txt
tic_toc-0.1.2.data/data/readme.md
tic_toc-0.1.2.dist-info/METADATA
tic_toc-0.1.2.dist-info/WHEEL
tic_toc-0.1.2.dist-info/license.txt
tic_toc-0.1.2.dist-info/top_level.txt
tic_toc-0.1.2.dist-info/RECORD
