Metadata-Version: 2.1
Name: tic-toc
Version: 0.1.2
Summary: Measure and track the wall and CPU time of defined scopes.
Home-page: https://github.com/nok/tic-toc/tree/stable
Author: Darius Morawiec
Author-email: ping@nok.onl
License: MIT
Keywords: time,timeit
Platform: UNKNOWN
Classifier: Programming Language :: Python :: 3.6
Classifier: Programming Language :: Python :: 3.7
